hdl_parser-1.1.0.dist-info/METADATA
hdl_parser-1.1.0.dist-info/WHEEL
hdl_parser-1.1.0.dist-info/entry_points.txt
hdl_parser-1.1.0.dist-info/licenses/LICENSE
hdl_parser/Templates/__init__.py
hdl_parser/Templates/instance_template
hdl_parser/Templates/instance_with_param_template
hdl_parser/__init__.py
hdl_parser/_datamodel.py
hdl_parser/_gen_templates.py
hdl_parser/_sv/__init__.py
hdl_parser/_sv/lexer.py
hdl_parser/_sv/parser.py
hdl_parser/_sv/token.py
hdl_parser/_vhdl/__init__.py
hdl_parser/_vhdl/lexer.py
hdl_parser/_vhdl/parser.py
hdl_parser/_vhdl/token.py
hdl_parser/cli.py
hdl_parser/datamodel.py
hdl_parser/filelistparser.py
hdl_parser/parser.py
hdl_parser-1.1.0.dist-info/RECORD
