Metadata-Version: 2.1
Name: hdl-parser
Version: 1.1.0
Summary: Easy-To-Use SystemVerilog Parser
Keywords: SystemVerilog,Verilog,Parser
Author-Email: Eric Macedo <ericsmacedo@gmail.com>, Daniel Jakschik <iccode17@gmail.com>
Classifier: Programming Language :: Python :: 3
Classifier: Programming Language :: Python :: 3.10
Classifier: Programming Language :: Python :: 3.11
Classifier: Programming Language :: Python :: 3.12
Classifier: Programming Language :: Python :: 3.13
Classifier: Programming Language :: Python :: 3.14
Classifier: Operating System :: OS Independent
Project-URL: Homepage, https://github.com/ericsmacedo/hdl-parser
Project-URL: Documentation, https://hdl-parser.readthedocs.io/en/stable/
Project-URL: Bug Tracker, https://github.com/ericsmacedo/hdl-parser/issues
Requires-Python: <4.0,>=3.10.0
Requires-Dist: click>=8.2.1
Requires-Dist: pygments>=2.19.1
Requires-Dist: jinja2>=3.1.6
Requires-Dist: pydantic>=2.11.5
Requires-Dist: rich>=14.0.0
